google/cloud/bigquery_datapolicies/__init__.py
google/cloud/bigquery_datapolicies/gapic_version.py
google/cloud/bigquery_datapolicies/py.typed
google/cloud/bigquery_datapolicies_v1/__init__.py
google/cloud/bigquery_datapolicies_v1/gapic_metadata.json
google/cloud/bigquery_datapolicies_v1/gapic_version.py
google/cloud/bigquery_datapolicies_v1/py.typed
google/cloud/bigquery_datapolicies_v1/services/__init__.py
google/cloud/bigquery_datapolicies_v1/services/data_policy_service/__init__.py
google/cloud/bigquery_datapolicies_v1/services/data_policy_service/async_client.py
google/cloud/bigquery_datapolicies_v1/services/data_policy_service/client.py
google/cloud/bigquery_datapolicies_v1/services/data_policy_service/pagers.py
google/cloud/bigquery_datapolicies_v1/services/data_policy_service/transports/__init__.py
google/cloud/bigquery_datapolicies_v1/services/data_policy_service/transports/base.py
google/cloud/bigquery_datapolicies_v1/services/data_policy_service/transports/grpc.py
google/cloud/bigquery_datapolicies_v1/services/data_policy_service/transports/grpc_asyncio.py
google/cloud/bigquery_datapolicies_v1/services/data_policy_service/transports/rest.py
google/cloud/bigquery_datapolicies_v1/services/data_policy_service/transports/rest_base.py
google/cloud/bigquery_datapolicies_v1/types/__init__.py
google/cloud/bigquery_datapolicies_v1/types/datapolicy.py
google/cloud/bigquery_datapolicies_v1beta1/__init__.py
google/cloud/bigquery_datapolicies_v1beta1/gapic_metadata.json
google/cloud/bigquery_datapolicies_v1beta1/gapic_version.py
google/cloud/bigquery_datapolicies_v1beta1/py.typed
google/cloud/bigquery_datapolicies_v1beta1/services/__init__.py
google/cloud/bigquery_datapolicies_v1beta1/services/data_policy_service/__init__.py
google/cloud/bigquery_datapolicies_v1beta1/services/data_policy_service/async_client.py
google/cloud/bigquery_datapolicies_v1beta1/services/data_policy_service/client.py
google_cloud_bigquery_datapolicies-0.8.0.dist-info/licenses/LICENSE
google_cloud_bigquery_datapolicies-0.8.0.dist-info/METADATA
google_cloud_bigquery_datapolicies-0.8.0.dist-info/WHEEL
google_cloud_bigquery_datapolicies-0.8.0.dist-info/top_level.txt
google_cloud_bigquery_datapolicies-0.8.0.dist-info/RECORD
